coredeco/__init__.py
coredeco-0.5.4.dist-info/WHEEL
coredeco-0.5.4.dist-info/entry_points.txt
coredeco-0.5.4.dist-info/METADATA
coredeco-0.5.4.dist-info/RECORD
