Metadata-Version: 2.3
Name: coredeco
Version: 0.5.4
Summary: Small package with helpful and various function decorators
Author: Xenely
Requires-Python: >=3.10
